jjrawlins_cdk_iam_policy_builder_helper/_jsii/__init__.py
jjrawlins_cdk_iam_policy_builder_helper/_jsii/cdk-iam-policy-builder-helper@0.0.134.jsii.tgz
jjrawlins_cdk_iam_policy_builder_helper-0.0.134.dist-info/LICENSE
jjrawlins_cdk_iam_policy_builder_helper-0.0.134.dist-info/METADATA
jjrawlins_cdk_iam_policy_builder_helper-0.0.134.dist-info/WHEEL
jjrawlins_cdk_iam_policy_builder_helper-0.0.134.dist-info/top_level.txt
jjrawlins_cdk_iam_policy_builder_helper-0.0.134.dist-info/RECORD
